bingwallpaperpy/__main__.py
bingwallpaperpy/bingwallpaper.py
bingwallpaperpy-0.1.5.dist-info/LICENSE
bingwallpaperpy-0.1.5.dist-info/METADATA
bingwallpaperpy-0.1.5.dist-info/WHEEL
bingwallpaperpy-0.1.5.dist-info/entry_points.txt
bingwallpaperpy-0.1.5.dist-info/RECORD
