Metadata-Version: 2.1
Name: bingwallpaperpy
Version: 0.1.5
Summary: Download script for Bing daily wallpapers.
Home-page: https://github.com/jkorinth/bingwallpaper-py
License: GPL-3.0-or-later
Author: Jens Korinth
Author-email: jkorinth@gmx.net
Requires-Python: >=3.7,<4.0
Classifier: License :: OSI Approved :: GNU General Public License v3 or later (GPLv3+)
Classifier: Programming Language :: Python :: 3
Classifier: Programming Language :: Python :: 3.7
Classifier: Programming Language :: Python :: 3.8
Classifier: Programming Language :: Python :: 3.9
Classifier: Programming Language :: Python :: 3.10
Classifier: Programming Language :: Python :: 3.11
Requires-Dist: black (>=23.3.0,<24.0.0)
Requires-Dist: pillow (>=9.4.0,<10.0.0)
Requires-Dist: requests (>=2.28.2,<3.0.0)
Project-URL: Repository, https://github.com/jkorinth/bingwallpaper-py
